CHANGELOG.txt
LISCENCE.txt
MANIFEST.in
README.txt
setup.py
database_lib/__init__.py
database_lib.egg-info/PKG-INFO
database_lib.egg-info/SOURCES.txt
database_lib.egg-info/dependency_links.txt
database_lib.egg-info/top_level.txt