Metadata-Version: 2.1
Name: database-lib
Version: 0.0.1
Summary: A basic sqlite3 editing library
Home-page: 
Author: Theodor Billek
Author-email: HilbertLooked@gmail.com
License: MIT
Keywords: database
Classifier: Development Status :: 5 - Production/Stable
Classifier: Intended Audience :: Education
Classifier: Operating System :: Microsoft :: Windows :: Windows 10
Classifier: License :: OSI Approved :: MIT License
Classifier: Programming Language :: Python :: 3
